sg2t/__init__.py
sg2t/config/__init__.py
sg2t/config/config.ini
sg2t/config/config.py
sg2t/config/paths.py
sg2t/extern/__init__.py
sg2t/fuels/__init__.py
sg2t/fuels/electrification.py
sg2t/io/__init__.py
sg2t/io/base.json
sg2t/io/base.py
sg2t/io/schemas.py
sg2t/io/loadshapes/__init__.py
sg2t/io/loadshapes/ev.py
sg2t/io/loadshapes/nrel/__init__.py
sg2t/io/loadshapes/nrel/api.py
sg2t/io/loadshapes/nrel/mapping.py
sg2t/io/loadshapes/nrel/naming.py
sg2t/io/loadshapes/nrel/resstock.json
sg2t/io/loadshapes/nrel/resstock.py
sg2t/io/weather/tmy3/__init__.py
sg2t/io/weather/tmy3/converters.py
sg2t/io/weather/tmy3/mapping.py
sg2t/io/weather/tmy3/tmy3.py
sg2t/io/weather/tmy3/tmy3_nrel.json
sg2t/io/weather/tmy3/tmy3_nrel_stock.json
sg2t/io/weather/tmy3/tmy3_nrel_stock.py
sg2t/loadshape/__init__.py
sg2t/loadshape/loadshape.py
sg2t/loadshape/loadshape_nrel.py
sg2t/transportation/__init__.py
sg2t/transportation/speech.py
sg2t/utils/__init__.py
sg2t/utils/io.py
sg2t/utils/saving.py
sg2t/utils/timeseries.py
sg2t/weather/__init__.py
sg2t/weather/weather.py
sg2t-0.1.1.dist-info/LICENSE
sg2t-0.1.1.dist-info/METADATA
sg2t-0.1.1.dist-info/WHEEL
sg2t-0.1.1.dist-info/top_level.txt
sg2t-0.1.1.dist-info/RECORD
