Metadata-Version: 2.1
Name: sg2t
Version: 0.1.1
Summary: SLAC GISMo Grid Tools is single core package for grid related data cleaning, manipulation and data science in Python.
Author: Mohamed Nijad 
Author-email: Sara Miskovich <smiskov@slac.stanford.edu>, David Chassin <dchassin@slac.stanford.edu>
License: BSD 3-Clause License
Project-URL: Homepage, https://github.com/slacgismo/sg2t
Project-URL: Documentation, https://sg2t.readthedocs.io/
Project-URL: Bug Tracker, https://github.com/slacgismo/sg2t/issues
Project-URL: Discussions, https://github.com/slacgismo/sg2t/discussions
Keywords: grid,load modeling,electric loadshapes
Classifier: Development Status :: 4 - Beta
Classifier: License :: OSI Approved :: BSD License
Classifier: Programming Language :: Python :: 3 :: Only
Classifier: Programming Language :: Python :: 3.6
Classifier: Programming Language :: Python :: 3.7
Classifier: Programming Language :: Python :: 3.8
Classifier: Programming Language :: Python :: 3.9
Classifier: Programming Language :: Python :: 3.10
Classifier: Programming Language :: Python :: 3.11
Classifier: Programming Language :: Python :: 3.12
Classifier: Intended Audience :: Science/Research
Classifier: Topic :: Scientific/Engineering
Requires-Python: >=3.6
License-File: LICENSE
Requires-Dist: numpy
Requires-Dist: pandas
Requires-Dist: jupyter
Requires-Dist: matplotlib
Requires-Dist: marimo
Provides-Extra: docs
Requires-Dist: sphinx ; extra == 'docs'
Requires-Dist: sphinx-changelog >=1.2.0 ; extra == 'docs'
Requires-Dist: sphinx-design ; extra == 'docs'
